[
  {
    "author": "SlenderGz",
    "link_thumb": "https://live.staticflickr.com/65535/51671297122_fd29548d69_o.gif",
    "link_bin": "https://github.com/lmbstudiocontact/mb4_10/raw/main/5762.bin",
    "id_bin": "5762",
    "list_language": [],
    "array_tags": [
      "digital",
      "date",
      "seconds",
      "girl",
      "battery",
      "steps",
      "anime"
    ],
    "list_album": [
      {
        "id_album": "63410260",
        "link_thumb": "https://live.staticflickr.com/65535/51671297122_fd29548d69_o.gif",
        "title": "Anime"
      }
    ]
  },
  {
    "author": "Jerryjie",
    "link_thumb": "https://live.staticflickr.com/65535/51671619762_66b0740f7d_o.gif",
    "link_bin": "https://github.com/lmbstudiocontact/mb4_25/raw/main/9.bin",
    "id_bin": "9",
    "list_language": [],
    "array_tags": [
      "battery",
      "steps"
    ],
    "list_album": [
      {
        "id_album": "63410260",
        "link_thumb": "https://live.staticflickr.com/65535/51671619762_66b0740f7d_o.gif",
        "title": "Anime"
      }
    ]
  },
  {
    "author": "LMB Studio",
    "link_thumb": "https://live.staticflickr.com/65535/51681980607_36000946bf_o.gif",
    "link_bin": "https://github.com/lmbstudiocontact/mb4_61/raw/main/One Piece Anime_L1_-1532342288.bin",
    "id_bin": "One Piece Anime_L1_-1532342288",
    "list_language": [
      {
        "author": "LMB Studio",
        "link_thumb": "https://live.staticflickr.com/65535/51681980797_ffe52318b2_o.gif",
        "link_bin": "https://github.com/lmbstudiocontact/mb4_61/raw/main/One Piece Anime_L1_-1532342288_English.bin",
        "name_language": "English",
        "id_bin_language": "One Piece Anime_L1_-1532342288_English"
      },
      {
        "author": "LMB Studio",
        "link_thumb": "https://live.staticflickr.com/65535/51683444529_6218751268_o.gif",
        "link_bin": "https://github.com/lmbstudiocontact/mb4_61/raw/main/One Piece Anime_L1_-1532342288_Portuguese.bin",
        "name_language": "Portuguese",
        "id_bin_language": "One Piece Anime_L1_-1532342288_Portuguese"
      },
      {
        "author": "LMB Studio",
        "link_thumb": "https://live.staticflickr.com/65535/51683444699_b4bdb88cd7_o.gif",
        "link_bin": "https://github.com/lmbstudiocontact/mb4_61/raw/main/One Piece Anime_L1_-1532342288_Russian.bin",
        "name_language": "Russian",
        "id_bin_language": "One Piece Anime_L1_-1532342288_Russian"
      },
      {
        "author": "LMB Studio",
        "link_thumb": "https://live.staticflickr.com/65535/51681981402_653f452280_o.gif",
        "link_bin": "https://github.com/lmbstudiocontact/mb4_61/raw/main/One Piece Anime_L1_-1532342288_Spanish.bin",
        "name_language": "Spanish",
        "id_bin_language": "One Piece Anime_L1_-1532342288_Spanish"
      }
    ],
    "array_tags": [
      "lmbstudio"
    ],
    "list_album": [
      {
        "id_album": "1351456604",
        "link_thumb": "https://live.staticflickr.com/65535/51681980607_36000946bf_o.gif",
        "title": "One Piece Anime_L1"
      }
    ]
  },
  {
    "author": "LMB Studio",
    "link_thumb": "https://live.staticflickr.com/65535/51688740830_8faf86de01_o.gif",
    "link_bin": "https://github.com/lmbstudiocontact/mb4_80/raw/main/Ragnarok_L9_-1835181947.bin",
    "id_bin": "Ragnarok_L9_-1835181947",
    "list_language": [
      {
        "author": "LMB Studio",
        "link_thumb": "https://live.staticflickr.com/65535/51687841336_daab818379_o.gif",
        "link_bin": "https://github.com/lmbstudiocontact/mb4_80/raw/main/Ragnarok_L9_-1835181947_English.bin",
        "name_language": "English",
        "id_bin_language": "Ragnarok_L9_-1835181947_English"
      },
      {
        "author": "LMB Studio",
        "link_thumb": "https://live.staticflickr.com/65535/51687841466_24de389188_o.gif",
        "link_bin": "https://github.com/lmbstudiocontact/mb4_80/raw/main/Ragnarok_L9_-1835181947_Portuguese.bin",
        "name_language": "Portuguese",
        "id_bin_language": "Ragnarok_L9_-1835181947_Portuguese"
      },
      {
        "author": "LMB Studio",
        "link_thumb": "https://live.staticflickr.com/65535/51688741265_6ca696a40b_o.gif",
        "link_bin": "https://github.com/lmbstudiocontact/mb4_80/raw/main/Ragnarok_L9_-1835181947_Russian.bin",
        "name_language": "Russian",
        "id_bin_language": "Ragnarok_L9_-1835181947_Russian"
      },
      {
        "author": "LMB Studio",
        "link_thumb": "https://live.staticflickr.com/65535/51687841846_ae689e521d_o.gif",
        "link_bin": "https://github.com/lmbstudiocontact/mb4_80/raw/main/Ragnarok_L9_-1835181947_Spanish.bin",
        "name_language": "Spanish",
        "id_bin_language": "Ragnarok_L9_-1835181947_Spanish"
      }
    ],
    "array_tags": [
      "lmbstudio"
    ],
    "list_album": [
      {
        "id_album": "1601322217",
        "link_thumb": "https://live.staticflickr.com/65535/51688740830_8faf86de01_o.gif",
        "title": "Ragnarok_L9"
      }
    ]
  },
  {
    "author": "LMB Studio",
    "link_thumb": "https://live.staticflickr.com/65535/51689208133_641e4d7b4c_o.gif",
    "link_bin": "https://github.com/lmbstudiocontact/mb4_30/raw/main/Simpsons Cartoon_L10_-1971876724.bin",
    "id_bin": "Simpsons Cartoon_L10_-1971876724",
    "list_language": [
      {
        "author": "LMB Studio",
        "link_thumb": "https://live.staticflickr.com/65535/51688937351_182875e825_o.gif",
        "link_bin": "https://github.com/lmbstudiocontact/mb4_30/raw/main/Simpsons Cartoon_L10_-1971876724_English.bin",
        "name_language": "English",
        "id_bin_language": "Simpsons Cartoon_L10_-1971876724_English"
      },
      {
        "author": "LMB Studio",
        "link_thumb": "https://live.staticflickr.com/65535/51688148617_a27f952fcb_o.gif",
        "link_bin": "https://github.com/lmbstudiocontact/mb4_30/raw/main/Simpsons Cartoon_L10_-1971876724_Portuguese.bin",
        "name_language": "Portuguese",
        "id_bin_language": "Simpsons Cartoon_L10_-1971876724_Portuguese"
      },
      {
        "author": "LMB Studio",
        "link_thumb": "https://live.staticflickr.com/65535/51688148992_501a5de71e_o.gif",
        "link_bin": "https://github.com/lmbstudiocontact/mb4_30/raw/main/Simpsons Cartoon_L10_-1971876724_Russian.bin",
        "name_language": "Russian",
        "id_bin_language": "Simpsons Cartoon_L10_-1971876724_Russian"
      },
      {
        "author": "LMB Studio",
        "link_thumb": "https://live.staticflickr.com/65535/51688149212_7a32b34654_o.gif",
        "link_bin": "https://github.com/lmbstudiocontact/mb4_30/raw/main/Simpsons Cartoon_L10_-1971876724_Spanish.bin",
        "name_language": "Spanish",
        "id_bin_language": "Simpsons Cartoon_L10_-1971876724_Spanish"
      }
    ],
    "array_tags": [
      "lmbstudio"
    ],
    "list_album": [
      {
        "id_album": "930638612",
        "link_thumb": "https://live.staticflickr.com/65535/51689208133_641e4d7b4c_o.gif",
        "title": "Simpsons Cartoon_L10"
      }
    ]
  },
  {
    "author": "LMB Studio",
    "link_thumb": "https://live.staticflickr.com/65535/51685345758_3491e6a09c_o.gif",
    "link_bin": "https://github.com/lmbstudiocontact/mb4_65/raw/main/One Piece Anime_L6_-41499124.bin",
    "id_bin": "One Piece Anime_L6_-41499124",
    "list_language": [
      {
        "author": "LMB Studio",
        "link_thumb": "https://live.staticflickr.com/65535/51685073991_e391320d96_o.gif",
        "link_bin": "https://github.com/lmbstudiocontact/mb4_65/raw/main/One Piece Anime_L6_-41499124_English.bin",
        "name_language": "English",
        "id_bin_language": "One Piece Anime_L6_-41499124_English"
      },
      {
        "author": "LMB Studio",
        "link_thumb": "https://live.staticflickr.com/65535/51685074181_c26a3dd50b_o.gif",
        "link_bin": "https://github.com/lmbstudiocontact/mb4_65/raw/main/One Piece Anime_L6_-41499124_Portuguese.bin",
        "name_language": "Portuguese",
        "id_bin_language": "One Piece Anime_L6_-41499124_Portuguese"
      },
      {
        "author": "LMB Studio",
        "link_thumb": "https://live.staticflickr.com/65535/51685757854_c72d372db8_o.gif",
        "link_bin": "https://github.com/lmbstudiocontact/mb4_65/raw/main/One Piece Anime_L6_-41499124_Russian.bin",
        "name_language": "Russian",
        "id_bin_language": "One Piece Anime_L6_-41499124_Russian"
      },
      {
        "author": "LMB Studio",
        "link_thumb": "https://live.staticflickr.com/65535/51685074501_0d77fcdddb_o.gif",
        "link_bin": "https://github.com/lmbstudiocontact/mb4_65/raw/main/One Piece Anime_L6_-41499124_Spanish.bin",
        "name_language": "Spanish",
        "id_bin_language": "One Piece Anime_L6_-41499124_Spanish"
      }
    ],
    "array_tags": [
      "lmbstudio"
    ],
    "list_album": [
      {
        "id_album": "1351456609",
        "link_thumb": "https://live.staticflickr.com/65535/51685345758_3491e6a09c_o.gif",
        "title": "One Piece Anime_L6"
      }
    ]
  },
  {
    "author": "tyler200298",
    "link_thumb": "https://live.staticflickr.com/65535/51670822022_db09c2f6c6_o.gif",
    "link_bin": "https://github.com/lmbstudiocontact/mb4_21/raw/main/18174.bin",
    "id_bin": "18174",
    "list_language": [],
    "array_tags": [
      "date",
      "digital",
      "analog",
      "battery"
    ],
    "list_album": [
      {
        "id_album": "2433880",
        "link_thumb": "https://live.staticflickr.com/65535/51670822022_db09c2f6c6_o.gif",
        "title": "None"
      }
    ]
  },
  {
    "author": "LMB Studio",
    "link_thumb": "https://live.staticflickr.com/65535/51681975848_898a5981e1_o.gif",
    "link_bin": "https://github.com/lmbstudiocontact/mb4_55/raw/main/Music_L10_1978706612.bin",
    "id_bin": "Music_L10_1978706612",
    "list_language": [
      {
        "author": "LMB Studio",
        "link_thumb": "https://live.staticflickr.com/65535/51682605910_bafed7f207_o.gif",
        "link_bin": "https://github.com/lmbstudiocontact/mb4_55/raw/main/Music_L10_1978706612_English.bin",
        "name_language": "English",
        "id_bin_language": "Music_L10_1978706612_English"
      },
      {
        "author": "LMB Studio",
        "link_thumb": "https://live.staticflickr.com/65535/51681716826_3b3fae093c_o.gif",
        "link_bin": "https://github.com/lmbstudiocontact/mb4_55/raw/main/Music_L10_1978706612_Portuguese.bin",
        "name_language": "Portuguese",
        "id_bin_language": "Music_L10_1978706612_Portuguese"
      },
      {
        "author": "LMB Studio",
        "link_thumb": "https://live.staticflickr.com/65535/51681717141_f1b4445873_o.gif",
        "link_bin": "https://github.com/lmbstudiocontact/mb4_55/raw/main/Music_L10_1978706612_Russian.bin",
        "name_language": "Russian",
        "id_bin_language": "Music_L10_1978706612_Russian"
      },
      {
        "author": "LMB Studio",
        "link_thumb": "https://live.staticflickr.com/65535/51682606885_cdf642a57b_o.gif",
        "link_bin": "https://github.com/lmbstudiocontact/mb4_55/raw/main/Music_L10_1978706612_Spanish.bin",
        "name_language": "Spanish",
        "id_bin_language": "Music_L10_1978706612_Spanish"
      }
    ],
    "array_tags": [
      "lmbstudio"
    ],
    "list_album": [
      {
        "id_album": "-1900558799",
        "link_thumb": "https://live.staticflickr.com/65535/51681975848_898a5981e1_o.gif",
        "title": "Music_L10"
      }
    ]
  },
  {
    "author": "LMB Studio",
    "link_thumb": "https://live.staticflickr.com/65535/51675920061_d3ae62aa0c_o.gif",
    "link_bin": "https://github.com/lmbstudiocontact/mb4_40/raw/main/Detective Conan_L3_-1997106536.bin",
    "id_bin": "Detective Conan_L3_-1997106536",
    "list_language": [
      {
        "author": "LMB Studio",
        "link_thumb": "https://live.staticflickr.com/65535/51676797870_b1f15d2345_o.gif",
        "link_bin": "https://github.com/lmbstudiocontact/mb4_40/raw/main/Detective Conan_L3_-1997106536_English.bin",
        "name_language": "English",
        "id_bin_language": "Detective Conan_L3_-1997106536_English"
      },
      {
        "author": "LMB Studio",
        "link_thumb": "https://live.staticflickr.com/65535/51675920416_2af00cde83_o.gif",
        "link_bin": "https://github.com/lmbstudiocontact/mb4_40/raw/main/Detective Conan_L3_-1997106536_Portuguese.bin",
        "name_language": "Portuguese",
        "id_bin_language": "Detective Conan_L3_-1997106536_Portuguese"
      },
      {
        "author": "LMB Studio",
        "link_thumb": "https://live.staticflickr.com/65535/51675920656_4695e86fa3_o.gif",
        "link_bin": "https://github.com/lmbstudiocontact/mb4_40/raw/main/Detective Conan_L3_-1997106536_Russian.bin",
        "name_language": "Russian",
        "id_bin_language": "Detective Conan_L3_-1997106536_Russian"
      },
      {
        "author": "LMB Studio",
        "link_thumb": "https://live.staticflickr.com/65535/51676166203_c4963bdb28_o.gif",
        "link_bin": "https://github.com/lmbstudiocontact/mb4_40/raw/main/Detective Conan_L3_-1997106536_Spanish.bin",
        "name_language": "Spanish",
        "id_bin_language": "Detective Conan_L3_-1997106536_Spanish"
      }
    ],
    "array_tags": [
      "lmbstudio"
    ],
    "list_album": [
      {
        "id_album": "-1285383390",
        "link_thumb": "https://live.staticflickr.com/65535/51675920061_d3ae62aa0c_o.gif",
        "title": "Detective Conan_L3"
      }
    ]
  },
  {
    "author": "LMB Studio",
    "link_thumb": "https://live.staticflickr.com/65535/51688156790_843ea78986_o.gif",
    "link_bin": "https://github.com/lmbstudiocontact/mb4_77/raw/main/Pokmon Anime_L7_137666270.bin",
    "id_bin": "Pokmon Anime_L7_137666270",
    "list_language": [],
    "array_tags": [
      "lmbstudio"
    ],
    "list_album": [
      {
        "id_album": "-555824138",
        "link_thumb": "https://live.staticflickr.com/65535/51688156790_843ea78986_o.gif",
        "title": "Pokmon Anime_L7"
      }
    ]
  },
  {
    "author": "LMB Studio",
    "link_thumb": "https://live.staticflickr.com/65535/51680967073_327b8a2448_o.gif",
    "link_bin": "https://github.com/lmbstudiocontact/mb4_51/raw/main/Kitty \u0026 My Melody_L8_-610786442.bin",
    "id_bin": "Kitty \u0026 My Melody_L8_-610786442",
    "list_language": [
      {
        "author": "LMB Studio",
        "link_thumb": "https://live.staticflickr.com/65535/51681595050_06fac562fa_o.gif",
        "link_bin": "https://github.com/lmbstudiocontact/mb4_51/raw/main/Kitty \u0026 My Melody_L8_-610786442_English.bin",
        "name_language": "English",
        "id_bin_language": "Kitty \u0026 My Melody_L8_-610786442_English"
      },
      {
        "author": "LMB Studio",
        "link_thumb": "https://live.staticflickr.com/65535/51681595235_03228b9ac9_o.gif",
        "link_bin": "https://github.com/lmbstudiocontact/mb4_51/raw/main/Kitty \u0026 My Melody_L8_-610786442_Portuguese.bin",
        "name_language": "Portuguese",
        "id_bin_language": "Kitty \u0026 My Melody_L8_-610786442_Portuguese"
      },
      {
        "author": "LMB Studio",
        "link_thumb": "https://live.staticflickr.com/65535/51680711621_9817663103_o.gif",
        "link_bin": "https://github.com/lmbstudiocontact/mb4_51/raw/main/Kitty \u0026 My Melody_L8_-610786442_Russian.bin",
        "name_language": "Russian",
        "id_bin_language": "Kitty \u0026 My Melody_L8_-610786442_Russian"
      },
      {
        "author": "LMB Studio",
        "link_thumb": "https://live.staticflickr.com/65535/51683439642_371d96476a_o.gif",
        "link_bin": "https://github.com/lmbstudiocontact/mb4_51/raw/main/Kitty \u0026 My Melody_L8_-610786442_Spanish.bin",
        "name_language": "Spanish",
        "id_bin_language": "Kitty \u0026 My Melody_L8_-610786442_Spanish"
      }
    ],
    "array_tags": [
      "lmbstudio"
    ],
    "list_album": [
      {
        "id_album": "-378480538",
        "link_thumb": "https://live.staticflickr.com/65535/51680967073_327b8a2448_o.gif",
        "title": "Kitty \u0026 My Melody_L8"
      }
    ]
  },
  {
    "author": "LMB Studio",
    "link_thumb": "https://live.staticflickr.com/65535/51676005921_508b3295a6_o.gif",
    "link_bin": "https://github.com/lmbstudiocontact/mb4_74/raw/main/Dragon Ball Anime_L4_-196522934.bin",
    "id_bin": "Dragon Ball Anime_L4_-196522934",
    "list_language": [
      {
        "author": "LMB Studio",
        "link_thumb": "https://live.staticflickr.com/65535/51675204727_e39db2de1c_o.gif",
        "link_bin": "https://github.com/lmbstudiocontact/mb4_74/raw/main/Dragon Ball Anime_L4_-196522934_English.bin",
        "name_language": "English",
        "id_bin_language": "Dragon Ball Anime_L4_-196522934_English"
      },
      {
        "author": "LMB Studio",
        "link_thumb": "https://live.staticflickr.com/65535/51676679929_8e9c700824_o.gif",
        "link_bin": "https://github.com/lmbstudiocontact/mb4_74/raw/main/Dragon Ball Anime_L4_-196522934_Portuguese.bin",
        "name_language": "Portuguese",
        "id_bin_language": "Dragon Ball Anime_L4_-196522934_Portuguese"
      },
      {
        "author": "LMB Studio",
        "link_thumb": "https://live.staticflickr.com/65535/51676884405_1557753f72_o.gif",
        "link_bin": "https://github.com/lmbstudiocontact/mb4_74/raw/main/Dragon Ball Anime_L4_-196522934_Russian.bin",
        "name_language": "Russian",
        "id_bin_language": "Dragon Ball Anime_L4_-196522934_Russian"
      },
      {
        "author": "LMB Studio",
        "link_thumb": "https://live.staticflickr.com/65535/51676680254_e8fcde037d_o.gif",
        "link_bin": "https://github.com/lmbstudiocontact/mb4_74/raw/main/Dragon Ball Anime_L4_-196522934_Spanish.bin",
        "name_language": "Spanish",
        "id_bin_language": "Dragon Ball Anime_L4_-196522934_Spanish"
      }
    ],
    "array_tags": [
      "lmbstudio"
    ],
    "list_album": [
      {
        "id_album": "1464725223",
        "link_thumb": "https://live.staticflickr.com/65535/51676005921_508b3295a6_o.gif",
        "title": "Dragon Ball Anime_L4"
      }
    ]
  },
  {
    "author": "LMB Studio",
    "link_thumb": "https://live.staticflickr.com/65535/51677993623_04b46af050_o.gif",
    "link_bin": "https://github.com/lmbstudiocontact/mb4_36/raw/main/Football_L10_2025840725.bin",
    "id_bin": "Football_L10_2025840725",
    "list_language": [
      {
        "author": "LMB Studio",
        "link_thumb": "https://live.staticflickr.com/65535/51677993798_3cdbdd5a8b_o.gif",
        "link_bin": "https://github.com/lmbstudiocontact/mb4_36/raw/main/Football_L10_2025840725_English.bin",
        "name_language": "English",
        "id_bin_language": "Football_L10_2025840725_English"
      },
      {
        "author": "LMB Studio",
        "link_thumb": "https://live.staticflickr.com/65535/51677744976_990632144e_o.gif",
        "link_bin": "https://github.com/lmbstudiocontact/mb4_36/raw/main/Football_L10_2025840725_Portuguese.bin",
        "name_language": "Portuguese",
        "id_bin_language": "Football_L10_2025840725_Portuguese"
      },
      {
        "author": "LMB Studio",
        "link_thumb": "https://live.staticflickr.com/65535/51678415994_095a3da9e1_o.gif",
        "link_bin": "https://github.com/lmbstudiocontact/mb4_36/raw/main/Football_L10_2025840725_Russian.bin",
        "name_language": "Russian",
        "id_bin_language": "Football_L10_2025840725_Russian"
      },
      {
        "author": "LMB Studio",
        "link_thumb": "https://live.staticflickr.com/65535/51676938402_659cbf0bd6_o.gif",
        "link_bin": "https://github.com/lmbstudiocontact/mb4_36/raw/main/Football_L10_2025840725_Spanish.bin",
        "name_language": "Spanish",
        "id_bin_language": "Football_L10_2025840725_Spanish"
      }
    ],
    "array_tags": [
      "lmbstudio"
    ],
    "list_album": [
      {
        "id_album": "1383093177",
        "link_thumb": "https://live.staticflickr.com/65535/51677993623_04b46af050_o.gif",
        "title": "Football_L10"
      }
    ]
  },
  {
    "author": "LMB Studio",
    "link_thumb": "https://live.staticflickr.com/65535/51678622067_44f25f8fb2_o.gif",
    "link_bin": "https://github.com/lmbstudiocontact/mb4_20/raw/main/Horror Art_L8_973701245.bin",
    "id_bin": "Horror Art_L8_973701245",
    "list_language": [
      {
        "author": "LMB Studio",
        "link_thumb": "https://live.staticflickr.com/65535/51680097939_306dabe8e6_o.gif",
        "link_bin": "https://github.com/lmbstudiocontact/mb4_20/raw/main/Horror Art_L8_973701245_English.bin",
        "name_language": "English",
        "id_bin_language": "Horror Art_L8_973701245_English"
      },
      {
        "author": "LMB Studio",
        "link_thumb": "https://live.staticflickr.com/65535/51678622687_60b5d0f200_o.gif",
        "link_bin": "https://github.com/lmbstudiocontact/mb4_20/raw/main/Horror Art_L8_973701245_Portuguese.bin",
        "name_language": "Portuguese",
        "id_bin_language": "Horror Art_L8_973701245_Portuguese"
      },
      {
        "author": "LMB Studio",
        "link_thumb": "https://live.staticflickr.com/65535/51680312015_08a0a0cc14_o.gif",
        "link_bin": "https://github.com/lmbstudiocontact/mb4_20/raw/main/Horror Art_L8_973701245_Russian.bin",
        "name_language": "Russian",
        "id_bin_language": "Horror Art_L8_973701245_Russian"
      },
      {
        "author": "LMB Studio",
        "link_thumb": "https://live.staticflickr.com/65535/51679425766_5e8073a3ae_o.gif",
        "link_bin": "https://github.com/lmbstudiocontact/mb4_20/raw/main/Horror Art_L8_973701245_Spanish.bin",
        "name_language": "Spanish",
        "id_bin_language": "Horror Art_L8_973701245_Spanish"
      }
    ],
    "array_tags": [
      "lmbstudio"
    ],
    "list_album": [
      {
        "id_album": "529377278",
        "link_thumb": "https://live.staticflickr.com/65535/51678622067_44f25f8fb2_o.gif",
        "title": "Horror Art_L8"
      }
    ]
  },
  {
    "author": "LMB Studio",
    "link_thumb": "https://live.staticflickr.com/65535/51675632491_55eae4272a_o.gif",
    "link_bin": "https://github.com/lmbstudiocontact/mb4_26/raw/main/Doraemon Anime_L5_128971162.bin",
    "id_bin": "Doraemon Anime_L5_128971162",
    "list_language": [
      {
        "author": "LMB Studio",
        "link_thumb": "https://live.staticflickr.com/65535/51675875863_17007535cf_o.gif",
        "link_bin": "https://github.com/lmbstudiocontact/mb4_26/raw/main/Doraemon Anime_L5_128971162_English.bin",
        "name_language": "English",
        "id_bin_language": "Doraemon Anime_L5_128971162_English"
      },
      {
        "author": "LMB Studio",
        "link_thumb": "https://live.staticflickr.com/65535/51675632801_2a03534b69_o.gif",
        "link_bin": "https://github.com/lmbstudiocontact/mb4_19/raw/main/Doraemon Anime_L5_128971162_Portuguese.bin",
        "name_language": "Portuguese",
        "id_bin_language": "Doraemon Anime_L5_128971162_Portuguese"
      },
      {
        "author": "LMB Studio",
        "link_thumb": "https://live.staticflickr.com/65535/51674831107_1815bd28c1_o.gif",
        "link_bin": "https://github.com/lmbstudiocontact/mb4_19/raw/main/Doraemon Anime_L5_128971162_Russian.bin",
        "name_language": "Russian",
        "id_bin_language": "Doraemon Anime_L5_128971162_Russian"
      },
      {
        "author": "LMB Studio",
        "link_thumb": "https://live.staticflickr.com/65535/51675876243_ed5687e67d_o.gif",
        "link_bin": "https://github.com/lmbstudiocontact/mb4_19/raw/main/Doraemon Anime_L5_128971162_Spanish.bin",
        "name_language": "Spanish",
        "id_bin_language": "Doraemon Anime_L5_128971162_Spanish"
      }
    ],
    "array_tags": [
      "lmbstudio"
    ],
    "list_album": [
      {
        "id_album": "405661395",
        "link_thumb": "https://live.staticflickr.com/65535/51675632491_55eae4272a_o.gif",
        "title": "Doraemon Anime_L5"
      }
    ]
  },
  {
    "author": "LMB Studio",
    "link_thumb": "https://live.staticflickr.com/65535/51680360214_221a8b5f26_o.gif",
    "link_bin": "https://github.com/lmbstudiocontact/mb4_22/raw/main/Joker Harley Quinn_L3_-698016792.bin",
    "id_bin": "Joker Harley Quinn_L3_-698016792",
    "list_language": [
      {
        "author": "LMB Studio",
        "link_thumb": "https://live.staticflickr.com/65535/51679943468_1643debfe8_o.gif",
        "link_bin": "https://github.com/lmbstudiocontact/mb4_22/raw/main/Joker Harley Quinn_L3_-698016792_English.bin",
        "name_language": "English",
        "id_bin_language": "Joker Harley Quinn_L3_-698016792_English"
      },
      {
        "author": "LMB Studio",
        "link_thumb": "https://live.staticflickr.com/65535/51679687871_deac2f0d3e_o.gif",
        "link_bin": "https://github.com/lmbstudiocontact/mb4_22/raw/main/Joker Harley Quinn_L3_-698016792_Portuguese.bin",
        "name_language": "Portuguese",
        "id_bin_language": "Joker Harley Quinn_L3_-698016792_Portuguese"
      },
      {
        "author": "LMB Studio",
        "link_thumb": "https://live.staticflickr.com/65535/51679944493_3ecb0580f0_o.gif",
        "link_bin": "https://github.com/lmbstudiocontact/mb4_22/raw/main/Joker Harley Quinn_L3_-698016792_Russian.bin",
        "name_language": "Russian",
        "id_bin_language": "Joker Harley Quinn_L3_-698016792_Russian"
      },
      {
        "author": "LMB Studio",
        "link_thumb": "https://live.staticflickr.com/65535/51680575910_29f3ba4c7e_o.gif",
        "link_bin": "https://github.com/lmbstudiocontact/mb4_22/raw/main/Joker Harley Quinn_L3_-698016792_Spanish.bin",
        "name_language": "Spanish",
        "id_bin_language": "Joker Harley Quinn_L3_-698016792_Spanish"
      }
    ],
    "array_tags": [
      "lmbstudio"
    ],
    "list_album": [
      {
        "id_album": "-2022175635",
        "link_thumb": "https://live.staticflickr.com/65535/51680360214_221a8b5f26_o.gif",
        "title": "Joker Harley Quinn_L3"
      }
    ]
  },
  {
    "author": "LMB Studio",
    "link_thumb": "https://live.staticflickr.com/65535/51686480217_3ea312c05a_o.gif",
    "link_bin": "https://github.com/lmbstudiocontact/mb4_77/raw/main/Pokmon Anime_L7_265105030.bin",
    "id_bin": "Pokmon Anime_L7_265105030",
    "list_language": [],
    "array_tags": [
      "lmbstudio"
    ],
    "list_album": [
      {
        "id_album": "-555824138",
        "link_thumb": "https://live.staticflickr.com/65535/51686480217_3ea312c05a_o.gif",
        "title": "Pokmon Anime_L7"
      }
    ]
  },
  {
    "author": "LMB Studio",
    "link_thumb": "https://live.staticflickr.com/65535/51673392693_3fce9842e2_o.gif",
    "link_bin": "https://github.com/lmbstudiocontact/mb4_33/raw/main/Boss Baby Cartoon_L3_2136152856.bin",
    "id_bin": "Boss Baby Cartoon_L3_2136152856",
    "list_language": [
      {
        "author": "LMB Studio",
        "link_thumb": "https://live.staticflickr.com/65535/51674024470_99ed37a481_o.gif",
        "link_bin": "https://github.com/lmbstudiocontact/mb4_33/raw/main/Boss Baby Cartoon_L3_2136152856_English.bin",
        "name_language": "English",
        "id_bin_language": "Boss Baby Cartoon_L3_2136152856_English"
      },
      {
        "author": "LMB Studio",
        "link_thumb": "https://live.staticflickr.com/65535/51674024650_18b5eeeb15_o.gif",
        "link_bin": "https://github.com/lmbstudiocontact/mb4_33/raw/main/Boss Baby Cartoon_L3_2136152856_Portuguese.bin",
        "name_language": "Portuguese",
        "id_bin_language": "Boss Baby Cartoon_L3_2136152856_Portuguese"
      },
      {
        "author": "LMB Studio",
        "link_thumb": "https://live.staticflickr.com/65535/51673829154_7a03c16bc1_o.gif",
        "link_bin": "https://github.com/lmbstudiocontact/mb4_33/raw/main/Boss Baby Cartoon_L3_2136152856_Russian.bin",
        "name_language": "Russian",
        "id_bin_language": "Boss Baby Cartoon_L3_2136152856_Russian"
      },
      {
        "author": "LMB Studio",
        "link_thumb": "https://live.staticflickr.com/65535/51672348012_249f11138b_o.gif",
        "link_bin": "https://github.com/lmbstudiocontact/mb4_33/raw/main/Boss Baby Cartoon_L3_2136152856_Spanish.bin",
        "name_language": "Spanish",
        "id_bin_language": "Boss Baby Cartoon_L3_2136152856_Spanish"
      }
    ],
    "array_tags": [
      "lmbstudio"
    ],
    "list_album": [
      {
        "id_album": "158762703",
        "link_thumb": "https://live.staticflickr.com/65535/51673392693_3fce9842e2_o.gif",
        "title": "Boss Baby Cartoon_L3"
      }
    ]
  },
  {
    "author": "LMB Studio",
    "link_thumb": "https://live.staticflickr.com/65535/51690231145_fae174a965_o.gif",
    "link_bin": "https://github.com/lmbstudiocontact/mb4_32/raw/main/Wolf_L10_-61613750.bin",
    "id_bin": "Wolf_L10_-61613750",
    "list_language": [
      {
        "author": "LMB Studio",
        "link_thumb": "https://live.staticflickr.com/65535/51690231290_4e7e2b99e5_o.gif",
        "link_bin": "https://github.com/lmbstudiocontact/mb4_32/raw/main/Wolf_L10_-61613750_English.bin",
        "name_language": "English",
        "id_bin_language": "Wolf_L10_-61613750_English"
      },
      {
        "author": "LMB Studio",
        "link_thumb": "https://live.staticflickr.com/65535/51689339416_26fee83334_o.gif",
        "link_bin": "https://github.com/lmbstudiocontact/mb4_32/raw/main/Wolf_L10_-61613750_Portuguese.bin",
        "name_language": "Portuguese",
        "id_bin_language": "Wolf_L10_-61613750_Portuguese"
      },
      {
        "author": "LMB Studio",
        "link_thumb": "https://live.staticflickr.com/65535/51688549397_378d810b41_o.gif",
        "link_bin": "https://github.com/lmbstudiocontact/mb4_32/raw/main/Wolf_L10_-61613750_Russian.bin",
        "name_language": "Russian",
        "id_bin_language": "Wolf_L10_-61613750_Russian"
      },
      {
        "author": "LMB Studio",
        "link_thumb": "https://live.staticflickr.com/65535/51690017824_b0509dcedc_o.gif",
        "link_bin": "https://github.com/lmbstudiocontact/mb4_32/raw/main/Wolf_L10_-61613750_Spanish.bin",
        "name_language": "Spanish",
        "id_bin_language": "Wolf_L10_-61613750_Spanish"
      }
    ],
    "array_tags": [
      "lmbstudio"
    ],
    "list_album": [
      {
        "id_album": "-76610530",
        "link_thumb": "https://live.staticflickr.com/65535/51690231145_fae174a965_o.gif",
        "title": "Wolf_L10"
      }
    ]
  },
  {
    "author": "giselevv",
    "link_thumb": "https://live.staticflickr.com/65535/51674605558_c47d0083a7_o.gif",
    "link_bin": "https://github.com/lmbstudiocontact/mb4_48/raw/main/20367.bin",
    "id_bin": "20367",
    "list_language": [],
    "array_tags": [
      "digital",
      "date",
      "battery",
      "steps",
      "animation"
    ],
    "list_album": [
      {
        "id_album": "-2075887794",
        "link_thumb": "https://live.staticflickr.com/65535/51674605558_c47d0083a7_o.gif",
        "title": "Cartoon"
      }
    ]
  },
  {
    "author": "qetu",
    "link_thumb": "https://live.staticflickr.com/65535/51672490390_63c874bd19_o.gif",
    "link_bin": "https://github.com/lmbstudiocontact/mb4_21/raw/main/18142.bin",
    "id_bin": "18142",
    "list_language": [],
    "array_tags": [
      "date",
      "digital",
      "seconds",
      "month",
      "distance",
      "pulse",
      "simple",
      "calories",
      "casio",
      "day",
      "steps"
    ],
    "list_album": [
      {
        "id_album": "2433880",
        "link_thumb": "https://live.staticflickr.com/65535/51672490390_63c874bd19_o.gif",
        "title": "None"
      }
    ]
  },
  {
    "author": "None",
    "link_thumb": "https://live.staticflickr.com/65535/51672153910_cec0930c64_o.gif",
    "link_bin": "https://github.com/lmbstudiocontact/mb4_0/raw/main/1106_Vietnamese.bin",
    "id_bin": "1106_Vietnamese",
    "list_language": [],
    "array_tags": [],
    "list_album": [
      {
        "id_album": "-849040121",
        "link_thumb": "https://live.staticflickr.com/65535/51672153910_cec0930c64_o.gif",
        "title": "Language Vietnamese"
      }
    ]
  },
  {
    "author": "lucasmant",
    "link_thumb": "https://live.staticflickr.com/65535/51672624410_a3145b6e31_o.gif",
    "link_bin": "https://github.com/lmbstudiocontact/mb4_6/raw/main/2699.bin",
    "id_bin": "2699",
    "list_language": [],
    "array_tags": [
      "digital",
      "date",
      "battery",
      "steps"
    ],
    "list_album": [
      {
        "id_album": "-1997428321",
        "link_thumb": "https://live.staticflickr.com/65535/51672624410_a3145b6e31_o.gif",
        "title": "Marvel"
      }
    ]
  },
  {
    "author": "LMB Studio",
    "link_thumb": "https://live.staticflickr.com/65535/51680109951_18ea4dc692_o.gif",
    "link_bin": "https://github.com/lmbstudiocontact/mb4_24/raw/main/Kitty \u0026 My Melody_L1_1569657062.bin",
    "id_bin": "Kitty \u0026 My Melody_L1_1569657062",
    "list_language": [
      {
        "author": "LMB Studio",
        "link_thumb": "https://live.staticflickr.com/65535/51680110156_c3559a2fb2_o.gif",
        "link_bin": "https://github.com/lmbstudiocontact/mb4_24/raw/main/Kitty \u0026 My Melody_L1_1569657062_English.bin",
        "name_language": "English",
        "id_bin_language": "Kitty \u0026 My Melody_L1_1569657062_English"
      },
      {
        "author": "LMB Studio",
        "link_thumb": "https://live.staticflickr.com/65535/51680364168_c5570044b0_o.gif",
        "link_bin": "https://github.com/lmbstudiocontact/mb4_24/raw/main/Kitty \u0026 My Melody_L1_1569657062_Portuguese.bin",
        "name_language": "Portuguese",
        "id_bin_language": "Kitty \u0026 My Melody_L1_1569657062_Portuguese"
      },
      {
        "author": "LMB Studio",
        "link_thumb": "https://live.staticflickr.com/65535/51680785129_f1a94fbb71_o.gif",
        "link_bin": "https://github.com/lmbstudiocontact/mb4_24/raw/main/Kitty \u0026 My Melody_L1_1569657062_Russian.bin",
        "name_language": "Russian",
        "id_bin_language": "Kitty \u0026 My Melody_L1_1569657062_Russian"
      },
      {
        "author": "LMB Studio",
        "link_thumb": "https://live.staticflickr.com/65535/51680364628_510108a84c_o.gif",
        "link_bin": "https://github.com/lmbstudiocontact/mb4_24/raw/main/Kitty \u0026 My Melody_L1_1569657062_Spanish.bin",
        "name_language": "Spanish",
        "id_bin_language": "Kitty \u0026 My Melody_L1_1569657062_Spanish"
      }
    ],
    "array_tags": [
      "lmbstudio"
    ],
    "list_album": [
      {
        "id_album": "-378480545",
        "link_thumb": "https://live.staticflickr.com/65535/51680109951_18ea4dc692_o.gif",
        "title": "Kitty \u0026 My Melody_L1"
      }
    ]
  },
  {
    "author": "LMB Studio",
    "link_thumb": "https://live.staticflickr.com/65535/51686429284_340abb3ce5_o.gif",
    "link_bin": "https://github.com/lmbstudiocontact/mb4_7/raw/main/Onmyoji_L9_1013081624.bin",
    "id_bin": "Onmyoji_L9_1013081624",
    "list_language": [
      {
        "author": "LMB Studio",
        "link_thumb": "https://live.staticflickr.com/65535/51684956867_107477ea45_o.gif",
        "link_bin": "https://github.com/lmbstudiocontact/mb4_7/raw/main/Onmyoji_L9_1013081624_English.bin",
        "name_language": "English",
        "id_bin_language": "Onmyoji_L9_1013081624_English"
      },
      {
        "author": "LMB Studio",
        "link_thumb": "https://live.staticflickr.com/65535/51685743056_7501d67150_o.gif",
        "link_bin": "https://github.com/lmbstudiocontact/mb4_7/raw/main/Onmyoji_L9_1013081624_Portuguese.bin",
        "name_language": "Portuguese",
        "id_bin_language": "Onmyoji_L9_1013081624_Portuguese"
      },
      {
        "author": "LMB Studio",
        "link_thumb": "https://live.staticflickr.com/65535/51684957137_5111b096f3_o.gif",
        "link_bin": "https://github.com/lmbstudiocontact/mb4_7/raw/main/Onmyoji_L9_1013081624_Russian.bin",
        "name_language": "Russian",
        "id_bin_language": "Onmyoji_L9_1013081624_Russian"
      },
      {
        "author": "LMB Studio",
        "link_thumb": "https://live.staticflickr.com/65535/51685743416_f922fbb42b_o.gif",
        "link_bin": "https://github.com/lmbstudiocontact/mb4_7/raw/main/Onmyoji_L9_1013081624_Spanish.bin",
        "name_language": "Spanish",
        "id_bin_language": "Onmyoji_L9_1013081624_Spanish"
      }
    ],
    "array_tags": [
      "lmbstudio"
    ],
    "list_album": [
      {
        "id_album": "389318921",
        "link_thumb": "https://live.staticflickr.com/65535/51686429284_340abb3ce5_o.gif",
        "title": "Onmyoji_L9"
      }
    ]
  },
  {
    "author": "LMB Studio",
    "link_thumb": "https://live.staticflickr.com/65535/51689218480_f4148f1a1d_o.gif",
    "link_bin": "https://github.com/lmbstudiocontact/mb4_27/raw/main/Seven deadly sins Anime_L7_12173417.bin",
    "id_bin": "Seven deadly sins Anime_L7_12173417",
    "list_language": [],
    "array_tags": [
      "lmbstudio"
    ],
    "list_album": [
      {
        "id_album": "1802210943",
        "link_thumb": "https://live.staticflickr.com/65535/51689218480_f4148f1a1d_o.gif",
        "title": "Seven deadly sins Anime_L7"
      }
    ]
  },
  {
    "author": "LMB Studio",
    "link_thumb": "https://live.staticflickr.com/65535/51673936040_14eaef52e3_o.gif",
    "link_bin": "https://github.com/lmbstudiocontact/mb4_33/raw/main/Boku No Hero Academia Anime_L8_1738910655.bin",
    "id_bin": "Boku No Hero Academia Anime_L8_1738910655",
    "list_language": [
      {
        "author": "LMB Studio",
        "link_thumb": "https://live.staticflickr.com/65535/51673740144_05b57c47e2_o.gif",
        "link_bin": "https://github.com/lmbstudiocontact/mb4_33/raw/main/Boku No Hero Academia Anime_L8_1738910655_English.bin",
        "name_language": "English",
        "id_bin_language": "Boku No Hero Academia Anime_L8_1738910655_English"
      },
      {
        "author": "LMB Studio",
        "link_thumb": "https://live.staticflickr.com/65535/51673304808_66a2b4924a_o.gif",
        "link_bin": "https://github.com/lmbstudiocontact/mb4_33/raw/main/Boku No Hero Academia Anime_L8_1738910655_Portuguese.bin",
        "name_language": "Portuguese",
        "id_bin_language": "Boku No Hero Academia Anime_L8_1738910655_Portuguese"
      },
      {
        "author": "LMB Studio",
        "link_thumb": "https://live.staticflickr.com/65535/51673304938_4305aa26b6_o.gif",
        "link_bin": "https://github.com/lmbstudiocontact/mb4_33/raw/main/Boku No Hero Academia Anime_L8_1738910655_Russian.bin",
        "name_language": "Russian",
        "id_bin_language": "Boku No Hero Academia Anime_L8_1738910655_Russian"
      },
      {
        "author": "LMB Studio",
        "link_thumb": "https://live.staticflickr.com/65535/51673740734_f2af6d3ce3_o.gif",
        "link_bin": "https://github.com/lmbstudiocontact/mb4_33/raw/main/Boku No Hero Academia Anime_L8_1738910655_Spanish.bin",
        "name_language": "Spanish",
        "id_bin_language": "Boku No Hero Academia Anime_L8_1738910655_Spanish"
      }
    ],
    "array_tags": [
      "lmbstudio"
    ],
    "list_album": [
      {
        "id_album": "197312546",
        "link_thumb": "https://live.staticflickr.com/65535/51673936040_14eaef52e3_o.gif",
        "title": "Boku No Hero Academia Anime_L8"
      }
    ]
  },
  {
    "author": "LMB Studio",
    "link_thumb": "https://live.staticflickr.com/65535/51686054633_a821ddd1b7_o.gif",
    "link_bin": "https://github.com/lmbstudiocontact/mb4_7/raw/main/Panda Art_L5_978675123.bin",
    "id_bin": "Panda Art_L5_978675123",
    "list_language": [
      {
        "author": "LMB Studio",
        "link_thumb": "https://live.staticflickr.com/65535/51686466339_244031613b_o.gif",
        "link_bin": "https://github.com/lmbstudiocontact/mb4_7/raw/main/Panda Art_L5_978675123_English.bin",
        "name_language": "English",
        "id_bin_language": "Panda Art_L5_978675123_English"
      },
      {
        "author": "LMB Studio",
        "link_thumb": "https://live.staticflickr.com/65535/51686680485_fe940945ac_o.gif",
        "link_bin": "https://github.com/lmbstudiocontact/mb4_7/raw/main/Panda Art_L5_978675123_Portuguese.bin",
        "name_language": "Portuguese",
        "id_bin_language": "Panda Art_L5_978675123_Portuguese"
      },
      {
        "author": "LMB Studio",
        "link_thumb": "https://live.staticflickr.com/65535/51686055083_df1ff9a34c_o.gif",
        "link_bin": "https://github.com/lmbstudiocontact/mb4_7/raw/main/Panda Art_L5_978675123_Russian.bin",
        "name_language": "Russian",
        "id_bin_language": "Panda Art_L5_978675123_Russian"
      },
      {
        "author": "LMB Studio",
        "link_thumb": "https://live.staticflickr.com/65535/51686055268_6a553654a5_o.gif",
        "link_bin": "https://github.com/lmbstudiocontact/mb4_7/raw/main/Panda Art_L5_978675123_Spanish.bin",
        "name_language": "Spanish",
        "id_bin_language": "Panda Art_L5_978675123_Spanish"
      }
    ],
    "array_tags": [
      "lmbstudio"
    ],
    "list_album": [
      {
        "id_album": "586574347",
        "link_thumb": "https://live.staticflickr.com/65535/51686054633_a821ddd1b7_o.gif",
        "title": "Panda Art_L5"
      }
    ]
  },
  {
    "author": "LMB Studio",
    "link_thumb": "https://live.staticflickr.com/65535/51685030464_5a2b32be55_o.gif",
    "link_bin": "https://github.com/lmbstudiocontact/mb4_62/raw/main/One Piece Anime_L2_1418188340.bin",
    "id_bin": "One Piece Anime_L2_1418188340",
    "list_language": [
      {
        "author": "LMB Studio",
        "link_thumb": "https://live.staticflickr.com/65535/51685030704_0696bea6ae_o.gif",
        "link_bin": "https://github.com/lmbstudiocontact/mb4_62/raw/main/One Piece Anime_L2_1418188340_English.bin",
        "name_language": "English",
        "id_bin_language": "One Piece Anime_L2_1418188340_English"
      },
      {
        "author": "LMB Studio",
        "link_thumb": "https://live.staticflickr.com/65535/51684622623_f6cf675fb0_o.gif",
        "link_bin": "https://github.com/lmbstudiocontact/mb4_62/raw/main/One Piece Anime_L2_1418188340_Portuguese.bin",
        "name_language": "Portuguese",
        "id_bin_language": "One Piece Anime_L2_1418188340_Portuguese"
      },
      {
        "author": "LMB Studio",
        "link_thumb": "https://live.staticflickr.com/65535/51685031509_ed8f06294a_o.gif",
        "link_bin": "https://github.com/lmbstudiocontact/mb4_62/raw/main/One Piece Anime_L2_1418188340_Russian.bin",
        "name_language": "Russian",
        "id_bin_language": "One Piece Anime_L2_1418188340_Russian"
      },
      {
        "author": "LMB Studio",
        "link_thumb": "https://live.staticflickr.com/65535/51685031919_c4035b92c8_o.gif",
        "link_bin": "https://github.com/lmbstudiocontact/mb4_62/raw/main/One Piece Anime_L2_1418188340_Spanish.bin",
        "name_language": "Spanish",
        "id_bin_language": "One Piece Anime_L2_1418188340_Spanish"
      }
    ],
    "array_tags": [
      "lmbstudio"
    ],
    "list_album": [
      {
        "id_album": "1351456605",
        "link_thumb": "https://live.staticflickr.com/65535/51685030464_5a2b32be55_o.gif",
        "title": "One Piece Anime_L2"
      }
    ]
  },
  {
    "author": "Hoatran1",
    "link_thumb": "https://live.staticflickr.com/65535/51671494461_4cd11e11b0_o.gif",
    "link_bin": "https://github.com/lmbstudiocontact/mb4_1/raw/main/17.bin",
    "id_bin": "17",
    "list_language": [],
    "array_tags": [
      "digital"
    ],
    "list_album": [
      {
        "id_album": "-2075887794",
        "link_thumb": "https://live.staticflickr.com/65535/51671494461_4cd11e11b0_o.gif",
        "title": "Cartoon"
      }
    ]
  },
  {
    "author": "Sacriface",
    "link_thumb": "https://live.staticflickr.com/65535/51671415111_a3f99e257d_o.gif",
    "link_bin": "https://github.com/lmbstudiocontact/mb4_17/raw/main/12704.bin",
    "id_bin": "12704",
    "list_language": [],
    "array_tags": [
      "distance",
      "heartrate",
      "calories",
      "battery",
      "steps"
    ],
    "list_album": [
      {
        "id_album": "518493952",
        "link_thumb": "https://live.staticflickr.com/65535/51671415111_a3f99e257d_o.gif",
        "title": "Other 0"
      }
    ]
  },
  {
    "author": "arthurg",
    "link_thumb": "https://live.staticflickr.com/65535/51673120620_8770a370a3_o.gif",
    "link_bin": "https://github.com/lmbstudiocontact/mb4_10/raw/main/6910.bin",
    "id_bin": "6910",
    "list_language": [],
    "array_tags": [
      "mengo",
      "soccer",
      "futebol",
      "flamengo"
    ],
    "list_album": [
      {
        "id_album": "1381221108",
        "link_thumb": "https://live.staticflickr.com/65535/51673120620_8770a370a3_o.gif",
        "title": "Football Old"
      }
    ]
  },
  {
    "author": "LMB Studio",
    "link_thumb": "https://live.staticflickr.com/65535/51675271984_336538466f_o.gif",
    "link_bin": "https://github.com/lmbstudiocontact/mb4_4/raw/main/Cute Art_L6_927173558.bin",
    "id_bin": "Cute Art_L6_927173558",
    "list_language": [
      {
        "author": "LMB Studio",
        "link_thumb": "https://live.staticflickr.com/65535/51675272234_ae1eec1b45_o.gif",
        "link_bin": "https://github.com/lmbstudiocontact/mb4_4/raw/main/Cute Art_L6_927173558_English.bin",
        "name_language": "English",
        "id_bin_language": "Cute Art_L6_927173558_English"
      },
      {
        "author": "LMB Studio",
        "link_thumb": "https://live.staticflickr.com/65535/51674842393_aab934d898_o.gif",
        "link_bin": "https://github.com/lmbstudiocontact/mb4_4/raw/main/Cute Art_L6_927173558_Portuguese.bin",
        "name_language": "Portuguese",
        "id_bin_language": "Cute Art_L6_927173558_Portuguese"
      },
      {
        "author": "LMB Studio",
        "link_thumb": "https://live.staticflickr.com/65535/51674842703_f46f26a012_o.gif",
        "link_bin": "https://github.com/lmbstudiocontact/mb4_4/raw/main/Cute Art_L6_927173558_Russian.bin",
        "name_language": "Russian",
        "id_bin_language": "Cute Art_L6_927173558_Russian"
      },
      {
        "author": "LMB Studio",
        "link_thumb": "https://live.staticflickr.com/65535/51675273034_63b222e062_o.gif",
        "link_bin": "https://github.com/lmbstudiocontact/mb4_4/raw/main/Cute Art_L6_927173558_Spanish.bin",
        "name_language": "Spanish",
        "id_bin_language": "Cute Art_L6_927173558_Spanish"
      }
    ],
    "array_tags": [
      "lmbstudio"
    ],
    "list_album": [
      {
        "id_album": "-629963485",
        "link_thumb": "https://live.staticflickr.com/65535/51675271984_336538466f_o.gif",
        "title": "Cute Art_L6"
      }
    ]
  },
  {
    "author": "LMB Studio",
    "link_thumb": "https://live.staticflickr.com/65535/51680491377_9f62df2020_o.gif",
    "link_bin": "https://github.com/lmbstudiocontact/mb4_54/raw/main/Mickey Cartoon_L3_-1099574979.bin",
    "id_bin": "Mickey Cartoon_L3_-1099574979",
    "list_language": [
      {
        "author": "LMB Studio",
        "link_thumb": "https://live.staticflickr.com/65535/51681544263_d67509f3e9_o.gif",
        "link_bin": "https://github.com/lmbstudiocontact/mb4_54/raw/main/Mickey Cartoon_L3_-1099574979_English.bin",
        "name_language": "English",
        "id_bin_language": "Mickey Cartoon_L3_-1099574979_English"
      },
      {
        "author": "LMB Studio",
        "link_thumb": "https://live.staticflickr.com/65535/51682171920_ab489a815b_o.gif",
        "link_bin": "https://github.com/lmbstudiocontact/mb4_54/raw/main/Mickey Cartoon_L3_-1099574979_Portuguese.bin",
        "name_language": "Portuguese",
        "id_bin_language": "Mickey Cartoon_L3_-1099574979_Portuguese"
      },
      {
        "author": "LMB Studio",
        "link_thumb": "https://live.staticflickr.com/65535/51681544738_1aae549d77_o.gif",
        "link_bin": "https://github.com/lmbstudiocontact/mb4_54/raw/main/Mickey Cartoon_L3_-1099574979_Russian.bin",
        "name_language": "Russian",
        "id_bin_language": "Mickey Cartoon_L3_-1099574979_Russian"
      },
      {
        "author": "LMB Studio",
        "link_thumb": "https://live.staticflickr.com/65535/51682172385_bafd589939_o.gif",
        "link_bin": "https://github.com/lmbstudiocontact/mb4_54/raw/main/Mickey Cartoon_L3_-1099574979_Spanish.bin",
        "name_language": "Spanish",
        "id_bin_language": "Mickey Cartoon_L3_-1099574979_Spanish"
      }
    ],
    "array_tags": [
      "lmbstudio"
    ],
    "list_album": [
      {
        "id_album": "1680949824",
        "link_thumb": "https://live.staticflickr.com/65535/51680491377_9f62df2020_o.gif",
        "title": "Mickey Cartoon_L3"
      }
    ]
  },
  {
    "author": "HLV",
    "link_thumb": "https://live.staticflickr.com/65535/51670638277_a46d26268d_o.gif",
    "link_bin": "https://github.com/lmbstudiocontact/mb4_17/raw/main/12979.bin",
    "id_bin": "12979",
    "list_language": [],
    "array_tags": [
      "date",
      "digital",
      "distance",
      "battery",
      "steps"
    ],
    "list_album": [
      {
        "id_album": "518493952",
        "link_thumb": "https://live.staticflickr.com/65535/51670638277_a46d26268d_o.gif",
        "title": "Other 0"
      }
    ]
  },
  {
    "author": "LMB Studio",
    "link_thumb": "https://live.staticflickr.com/65535/51679914621_b12bd8f1fe_o.gif",
    "link_bin": "https://github.com/lmbstudiocontact/mb4_23/raw/main/Joker Harley Quinn_L9_687483068.bin",
    "id_bin": "Joker Harley Quinn_L9_687483068",
    "list_language": [
      {
        "author": "LMB Studio",
        "link_thumb": "https://live.staticflickr.com/65535/51680169258_0bc7c617a0_o.gif",
        "link_bin": "https://github.com/lmbstudiocontact/mb4_23/raw/main/Joker Harley Quinn_L9_687483068_English.bin",
        "name_language": "English",
        "id_bin_language": "Joker Harley Quinn_L9_687483068_English"
      },
      {
        "author": "LMB Studio",
        "link_thumb": "https://live.staticflickr.com/65535/51680803865_1c6a296a39_o.gif",
        "link_bin": "https://github.com/lmbstudiocontact/mb4_23/raw/main/Joker Harley Quinn_L9_687483068_Portuguese.bin",
        "name_language": "Portuguese",
        "id_bin_language": "Joker Harley Quinn_L9_687483068_Portuguese"
      },
      {
        "author": "LMB Studio",
        "link_thumb": "https://live.staticflickr.com/65535/51679915726_24b202af8f_o.gif",
        "link_bin": "https://github.com/lmbstudiocontact/mb4_23/raw/main/Joker Harley Quinn_L9_687483068_Russian.bin",
        "name_language": "Russian",
        "id_bin_language": "Joker Harley Quinn_L9_687483068_Russian"
      },
      {
        "author": "LMB Studio",
        "link_thumb": "https://live.staticflickr.com/65535/51679916146_6422176f65_o.gif",
        "link_bin": "https://github.com/lmbstudiocontact/mb4_23/raw/main/Joker Harley Quinn_L9_687483068_Spanish.bin",
        "name_language": "Spanish",
        "id_bin_language": "Joker Harley Quinn_L9_687483068_Spanish"
      }
    ],
    "array_tags": [
      "lmbstudio"
    ],
    "list_album": [
      {
        "id_album": "-2022175629",
        "link_thumb": "https://live.staticflickr.com/65535/51679914621_b12bd8f1fe_o.gif",
        "title": "Joker Harley Quinn_L9"
      }
    ]
  },
  {
    "author": "LMB Studio",
    "link_thumb": "https://live.staticflickr.com/65535/51685811596_467a189a45_o.gif",
    "link_bin": "https://github.com/lmbstudiocontact/mb4_70/raw/main/Plants Vs Zombies_L10_626372311.bin",
    "id_bin": "Plants Vs Zombies_L10_626372311",
    "list_language": [
      {
        "author": "LMB Studio",
        "link_thumb": "https://live.staticflickr.com/65535/51686087153_1af08cfa95_o.gif",
        "link_bin": "https://github.com/lmbstudiocontact/mb4_70/raw/main/Plants Vs Zombies_L10_626372311_English.bin",
        "name_language": "English",
        "id_bin_language": "Plants Vs Zombies_L10_626372311_English"
      },
      {
        "author": "LMB Studio",
        "link_thumb": "https://live.staticflickr.com/65535/51686712860_a515c8b533_o.gif",
        "link_bin": "https://github.com/lmbstudiocontact/mb4_70/raw/main/Plants Vs Zombies_L10_626372311_Portuguese.bin",
        "name_language": "Portuguese",
        "id_bin_language": "Plants Vs Zombies_L10_626372311_Portuguese"
      },
      {
        "author": "LMB Studio",
        "link_thumb": "https://live.staticflickr.com/65535/51686087513_7aae0ba2e8_o.gif",
        "link_bin": "https://github.com/lmbstudiocontact/mb4_70/raw/main/Plants Vs Zombies_L10_626372311_Russian.bin",
        "name_language": "Russian",
        "id_bin_language": "Plants Vs Zombies_L10_626372311_Russian"
      },
      {
        "author": "LMB Studio",
        "link_thumb": "https://live.staticflickr.com/65535/51686713195_36d73b37bc_o.gif",
        "link_bin": "https://github.com/lmbstudiocontact/mb4_70/raw/main/Plants Vs Zombies_L10_626372311_Spanish.bin",
        "name_language": "Spanish",
        "id_bin_language": "Plants Vs Zombies_L10_626372311_Spanish"
      }
    ],
    "array_tags": [
      "lmbstudio"
    ],
    "list_album": [
      {
        "id_album": "-1280428562",
        "link_thumb": "https://live.staticflickr.com/65535/51685811596_467a189a45_o.gif",
        "title": "Plants Vs Zombies_L10"
      }
    ]
  },
  {
    "author": "LMB Studio",
    "link_thumb": "https://live.staticflickr.com/65535/51676545970_49f548302f_o.gif",
    "link_bin": "https://github.com/lmbstudiocontact/mb4_19/raw/main/Doraemon Anime_L9_779547446.bin",
    "id_bin": "Doraemon Anime_L9_779547446",
    "list_language": [
      {
        "author": "LMB Studio",
        "link_thumb": "https://live.staticflickr.com/65535/51675913763_5f6084b92b_o.gif",
        "link_bin": "https://github.com/lmbstudiocontact/mb4_19/raw/main/Doraemon Anime_L9_779547446_English.bin",
        "name_language": "English",
        "id_bin_language": "Doraemon Anime_L9_779547446_English"
      },
      {
        "author": "LMB Studio",
        "link_thumb": "https://live.staticflickr.com/65535/51674867887_f8500e5ffe_o.gif",
        "link_bin": "https://github.com/lmbstudiocontact/mb4_19/raw/main/Doraemon Anime_L9_779547446_Portuguese.bin",
        "name_language": "Portuguese",
        "id_bin_language": "Doraemon Anime_L9_779547446_Portuguese"
      },
      {
        "author": "LMB Studio",
        "link_thumb": "https://live.staticflickr.com/65535/51676546355_5b01cc1679_o.gif",
        "link_bin": "https://github.com/lmbstudiocontact/mb4_19/raw/main/Doraemon Anime_L9_779547446_Russian.bin",
        "name_language": "Russian",
        "id_bin_language": "Doraemon Anime_L9_779547446_Russian"
      },
      {
        "author": "LMB Studio",
        "link_thumb": "https://live.staticflickr.com/65535/51674868227_872b52c6fc_o.gif",
        "link_bin": "https://github.com/lmbstudiocontact/mb4_19/raw/main/Doraemon Anime_L9_779547446_Spanish.bin",
        "name_language": "Spanish",
        "id_bin_language": "Doraemon Anime_L9_779547446_Spanish"
      }
    ],
    "array_tags": [
      "lmbstudio"
    ],
    "list_album": [
      {
        "id_album": "405661399",
        "link_thumb": "https://live.staticflickr.com/65535/51676545970_49f548302f_o.gif",
        "title": "Doraemon Anime_L9"
      }
    ]
  },
  {
    "author": "LMB Studio",
    "link_thumb": "https://live.staticflickr.com/65535/51675834908_6d36cab5e3_o.gif",
    "link_bin": "https://github.com/lmbstudiocontact/mb4_26/raw/main/Doraemon Anime_L2_1251911130.bin",
    "id_bin": "Doraemon Anime_L2_1251911130",
    "list_language": [
      {
        "author": "LMB Studio",
        "link_thumb": "https://live.staticflickr.com/65535/51676468640_ff6b06c5be_o.gif",
        "link_bin": "https://github.com/lmbstudiocontact/mb4_26/raw/main/Doraemon Anime_L2_1251911130_English.bin",
        "name_language": "English",
        "id_bin_language": "Doraemon Anime_L2_1251911130_English"
      },
      {
        "author": "LMB Studio",
        "link_thumb": "https://live.staticflickr.com/65535/51676468790_d09eb7bd89_o.gif",
        "link_bin": "https://github.com/lmbstudiocontact/mb4_26/raw/main/Doraemon Anime_L2_1251911130_Portuguese.bin",
        "name_language": "Portuguese",
        "id_bin_language": "Doraemon Anime_L2_1251911130_Portuguese"
      },
      {
        "author": "LMB Studio",
        "link_thumb": "https://live.staticflickr.com/65535/51675835283_d0b0769a4f_o.gif",
        "link_bin": "https://github.com/lmbstudiocontact/mb4_26/raw/main/Doraemon Anime_L2_1251911130_Russian.bin",
        "name_language": "Russian",
        "id_bin_language": "Doraemon Anime_L2_1251911130_Russian"
      },
      {
        "author": "LMB Studio",
        "link_thumb": "https://live.staticflickr.com/65535/51674790282_86d73bddc1_o.gif",
        "link_bin": "https://github.com/lmbstudiocontact/mb4_26/raw/main/Doraemon Anime_L2_1251911130_Spanish.bin",
        "name_language": "Spanish",
        "id_bin_language": "Doraemon Anime_L2_1251911130_Spanish"
      }
    ],
    "array_tags": [
      "lmbstudio"
    ],
    "list_album": [
      {
        "id_album": "405661392",
        "link_thumb": "https://live.staticflickr.com/65535/51675834908_6d36cab5e3_o.gif",
        "title": "Doraemon Anime_L2"
      }
    ]
  },
  {
    "author": "LMB Studio",
    "link_thumb": "https://live.staticflickr.com/65535/51677584647_16ef02fbf3_o.gif",
    "link_bin": "https://github.com/lmbstudiocontact/mb4_43/raw/main/Halloween Ghost Witch_L10_-972427424.bin",
    "id_bin": "Halloween Ghost Witch_L10_-972427424",
    "list_language": [
      {
        "author": "LMB Studio",
        "link_thumb": "https://live.staticflickr.com/65535/51679059599_553a5732ff_o.gif",
        "link_bin": "https://github.com/lmbstudiocontact/mb4_43/raw/main/Halloween Ghost Witch_L10_-972427424_English.bin",
        "name_language": "English",
        "id_bin_language": "Halloween Ghost Witch_L10_-972427424_English"
      },
      {
        "author": "LMB Studio",
        "link_thumb": "https://live.staticflickr.com/65535/51677585042_e2fbb3f046_o.gif",
        "link_bin": "https://github.com/lmbstudiocontact/mb4_43/raw/main/Halloween Ghost Witch_L10_-972427424_Portuguese.bin",
        "name_language": "Portuguese",
        "id_bin_language": "Halloween Ghost Witch_L10_-972427424_Portuguese"
      },
      {
        "author": "LMB Studio",
        "link_thumb": "https://live.staticflickr.com/65535/51677585172_a98131b37d_o.gif",
        "link_bin": "https://github.com/lmbstudiocontact/mb4_43/raw/main/Halloween Ghost Witch_L10_-972427424_Russian.bin",
        "name_language": "Russian",
        "id_bin_language": "Halloween Ghost Witch_L10_-972427424_Russian"
      },
      {
        "author": "LMB Studio",
        "link_thumb": "https://live.staticflickr.com/65535/51678388801_119e75ca03_o.gif",
        "link_bin": "https://github.com/lmbstudiocontact/mb4_43/raw/main/Halloween Ghost Witch_L10_-972427424_Spanish.bin",
        "name_language": "Spanish",
        "id_bin_language": "Halloween Ghost Witch_L10_-972427424_Spanish"
      }
    ],
    "array_tags": [
      "lmbstudio"
    ],
    "list_album": [
      {
        "id_album": "-1690866577",
        "link_thumb": "https://live.staticflickr.com/65535/51677584647_16ef02fbf3_o.gif",
        "title": "Halloween Ghost Witch_L10"
      }
    ]
  },
  {
    "author": "LMB Studio",
    "link_thumb": "https://live.staticflickr.com/65535/51685469923_2364f9c63d_o.gif",
    "link_bin": "https://github.com/lmbstudiocontact/mb4_65/raw/main/One Piece Anime_L8_-1418593334.bin",
    "id_bin": "One Piece Anime_L8_-1418593334",
    "list_language": [
      {
        "author": "LMB Studio",
        "link_thumb": "https://live.staticflickr.com/65535/51685196401_3c23e87cdd_o.gif",
        "link_bin": "https://github.com/lmbstudiocontact/mb4_65/raw/main/One Piece Anime_L8_-1418593334_English.bin",
        "name_language": "English",
        "id_bin_language": "One Piece Anime_L8_-1418593334_English"
      },
      {
        "author": "LMB Studio",
        "link_thumb": "https://live.staticflickr.com/65535/51685196596_211d7a1006_o.gif",
        "link_bin": "https://github.com/lmbstudiocontact/mb4_65/raw/main/One Piece Anime_L8_-1418593334_Portuguese.bin",
        "name_language": "Portuguese",
        "id_bin_language": "One Piece Anime_L8_-1418593334_Portuguese"
      },
      {
        "author": "LMB Studio",
        "link_thumb": "https://live.staticflickr.com/65535/51685881264_262b6b677b_o.gif",
        "link_bin": "https://github.com/lmbstudiocontact/mb4_65/raw/main/One Piece Anime_L8_-1418593334_Russian.bin",
        "name_language": "Russian",
        "id_bin_language": "One Piece Anime_L8_-1418593334_Russian"
      },
      {
        "author": "LMB Studio",
        "link_thumb": "https://live.staticflickr.com/65535/51685470763_7d64bd2957_o.gif",
        "link_bin": "https://github.com/lmbstudiocontact/mb4_65/raw/main/One Piece Anime_L8_-1418593334_Spanish.bin",
        "name_language": "Spanish",
        "id_bin_language": "One Piece Anime_L8_-1418593334_Spanish"
      }
    ],
    "array_tags": [
      "lmbstudio"
    ],
    "list_album": [
      {
        "id_album": "1351456611",
        "link_thumb": "https://live.staticflickr.com/65535/51685469923_2364f9c63d_o.gif",
        "title": "One Piece Anime_L8"
      }
    ]
  },
  {
    "author": "Chargez",
    "link_thumb": "https://live.staticflickr.com/65535/51675116999_c064faa2e2_o.gif",
    "link_bin": "https://github.com/lmbstudiocontact/mb4_49/raw/main/20927.bin",
    "id_bin": "20927",
    "list_language": [],
    "array_tags": [
      "digital",
      "battery",
      "steps"
    ],
    "list_album": [
      {
        "id_album": "63410260",
        "link_thumb": "https://live.staticflickr.com/65535/51675116999_c064faa2e2_o.gif",
        "title": "Anime"
      }
    ]
  },
  {
    "author": "T1MOXA",
    "link_thumb": "https://live.staticflickr.com/65535/51671116532_2c70dd4c28_o.gif",
    "link_bin": "https://github.com/lmbstudiocontact/mb4_66/raw/main/4158.bin",
    "id_bin": "4158",
    "list_language": [],
    "array_tags": [
      "digital",
      "date",
      "distance",
      "heartrate",
      "battery",
      "steps",
      "colors"
    ],
    "list_album": [
      {
        "id_album": "518493955",
        "link_thumb": "https://live.staticflickr.com/65535/51671116532_2c70dd4c28_o.gif",
        "title": "Other 3"
      }
    ]
  },
  {
    "author": "LMB Studio",
    "link_thumb": "https://live.staticflickr.com/65535/51674180439_af77ec0546_o.gif",
    "link_bin": "https://github.com/lmbstudiocontact/mb4_13/raw/main/Couple_L3_528332879.bin",
    "id_bin": "Couple_L3_528332879",
    "list_language": [
      {
        "author": "LMB Studio",
        "link_thumb": "https://live.staticflickr.com/65535/51674379965_862c1cf14f_o.gif",
        "link_bin": "https://github.com/lmbstudiocontact/mb4_13/raw/main/Couple_L3_528332879_English.bin",
        "name_language": "English",
        "id_bin_language": "Couple_L3_528332879_English"
      },
      {
        "author": "LMB Studio",
        "link_thumb": "https://live.staticflickr.com/65535/51673746388_0f25b3b7d7_o.gif",
        "link_bin": "https://github.com/lmbstudiocontact/mb4_13/raw/main/Couple_L3_528332879_Portuguese.bin",
        "name_language": "Portuguese",
        "id_bin_language": "Couple_L3_528332879_Portuguese"
      },
      {
        "author": "LMB Studio",
        "link_thumb": "https://live.staticflickr.com/65535/51674180979_cda89d1f51_o.gif",
        "link_bin": "https://github.com/lmbstudiocontact/mb4_13/raw/main/Couple_L3_528332879_Russian.bin",
        "name_language": "Russian",
        "id_bin_language": "Couple_L3_528332879_Russian"
      },
      {
        "author": "LMB Studio",
        "link_thumb": "https://live.staticflickr.com/65535/51673509571_da78b5c68c_o.gif",
        "link_bin": "https://github.com/lmbstudiocontact/mb4_13/raw/main/Couple_L3_528332879_Spanish.bin",
        "name_language": "Spanish",
        "id_bin_language": "Couple_L3_528332879_Spanish"
      }
    ],
    "array_tags": [
      "lmbstudio"
    ],
    "list_album": [
      {
        "id_album": "-888889818",
        "link_thumb": "https://live.staticflickr.com/65535/51674180439_af77ec0546_o.gif",
        "title": "Couple_L3"
      }
    ]
  },
  {
    "author": "matteusaugusto",
    "link_thumb": "https://live.staticflickr.com/65535/51675199375_8f38dfb6c3_o.gif",
    "link_bin": "https://github.com/lmbstudiocontact/mb4_48/raw/main/20137.bin",
    "id_bin": "20137",
    "list_language": [],
    "array_tags": [
      "analog",
      "art"
    ],
    "list_album": [
      {
        "id_album": "-1956005621",
        "link_thumb": "https://live.staticflickr.com/65535/51675199375_8f38dfb6c3_o.gif",
        "title": "None_2"
      }
    ]
  },
  {
    "author": "caamibss",
    "link_thumb": "https://live.staticflickr.com/65535/51674465308_48d8cc0e6b_o.gif",
    "link_bin": "https://github.com/lmbstudiocontact/mb4_48/raw/main/19402.bin",
    "id_bin": "19402",
    "list_language": [],
    "array_tags": [
      "digital",
      "date",
      "battery",
      "steps"
    ],
    "list_album": [
      {
        "id_album": "-1956005621",
        "link_thumb": "https://live.staticflickr.com/65535/51674465308_48d8cc0e6b_o.gif",
        "title": "None_2"
      }
    ]
  },
  {
    "author": "DenisML",
    "link_thumb": "https://live.staticflickr.com/65535/51672081081_490e2a268e_o.gif",
    "link_bin": "https://github.com/lmbstudiocontact/mb4_10/raw/main/5622.bin",
    "id_bin": "5622",
    "list_language": [],
    "array_tags": [
      "digital",
      "date",
      "analog",
      "seconds",
      "battery"
    ],
    "list_album": [
      {
        "id_album": "2092863",
        "link_thumb": "https://live.staticflickr.com/65535/51672081081_490e2a268e_o.gif",
        "title": "Cars"
      }
    ]
  },
  {
    "author": "LMB Studio",
    "link_thumb": "https://live.staticflickr.com/65535/51674032119_65d13ce472_o.gif",
    "link_bin": "https://github.com/lmbstudiocontact/mb4_34/raw/main/Buddhist Terms_L8_475028388.bin",
    "id_bin": "Buddhist Terms_L8_475028388",
    "list_language": [
      {
        "author": "LMB Studio",
        "link_thumb": "https://live.staticflickr.com/65535/51673596698_d723e6cbae_o.gif",
        "link_bin": "https://github.com/lmbstudiocontact/mb4_34/raw/main/Buddhist Terms_L8_475028388_English.bin",
        "name_language": "English",
        "id_bin_language": "Buddhist Terms_L8_475028388_English"
      },
      {
        "author": "LMB Studio",
        "link_thumb": "https://live.staticflickr.com/65535/51674032464_b67e7d2cc2_o.gif",
        "link_bin": "https://github.com/lmbstudiocontact/mb4_34/raw/main/Buddhist Terms_L8_475028388_Portuguese.bin",
        "name_language": "Portuguese",
        "id_bin_language": "Buddhist Terms_L8_475028388_Portuguese"
      },
      {
        "author": "LMB Studio",
        "link_thumb": "https://live.staticflickr.com/65535/51674230615_0f2c8972fe_o.gif",
        "link_bin": "https://github.com/lmbstudiocontact/mb4_34/raw/main/Buddhist Terms_L8_475028388_Russian.bin",
        "name_language": "Russian",
        "id_bin_language": "Buddhist Terms_L8_475028388_Russian"
      },
      {
        "author": "LMB Studio",
        "link_thumb": "https://live.staticflickr.com/65535/51674032839_33559dd46a_o.gif",
        "link_bin": "https://github.com/lmbstudiocontact/mb4_34/raw/main/Buddhist Terms_L8_475028388_Spanish.bin",
        "name_language": "Spanish",
        "id_bin_language": "Buddhist Terms_L8_475028388_Spanish"
      }
    ],
    "array_tags": [
      "lmbstudio"
    ],
    "list_album": [
      {
        "id_album": "518853935",
        "link_thumb": "https://live.staticflickr.com/65535/51674032119_65d13ce472_o.gif",
        "title": "Buddhist Terms_L8"
      }
    ]
  },
  {
    "author": "LMB Studio",
    "link_thumb": "https://live.staticflickr.com/65535/51676272964_9e1a78538a_o.gif",
    "link_bin": "https://github.com/lmbstudiocontact/mb4_26/raw/main/Doraemon Anime_L2_653215825.bin",
    "id_bin": "Doraemon Anime_L2_653215825",
    "list_language": [
      {
        "author": "LMB Studio",
        "link_thumb": "https://live.staticflickr.com/65535/51676273194_8c90ac4f27_o.gif",
        "link_bin": "https://github.com/lmbstudiocontact/mb4_26/raw/main/Doraemon Anime_L2_653215825_English.bin",
        "name_language": "English",
        "id_bin_language": "Doraemon Anime_L2_653215825_English"
      },
      {
        "author": "LMB Studio",
        "link_thumb": "https://live.staticflickr.com/65535/51674796407_3e6b757b1c_o.gif",
        "link_bin": "https://github.com/lmbstudiocontact/mb4_26/raw/main/Doraemon Anime_L2_653215825_Portuguese.bin",
        "name_language": "Portuguese",
        "id_bin_language": "Doraemon Anime_L2_653215825_Portuguese"
      },
      {
        "author": "LMB Studio",
        "link_thumb": "https://live.staticflickr.com/65535/51675599111_29aceafe1b_o.gif",
        "link_bin": "https://github.com/lmbstudiocontact/mb4_26/raw/main/Doraemon Anime_L2_653215825_Russian.bin",
        "name_language": "Russian",
        "id_bin_language": "Doraemon Anime_L2_653215825_Russian"
      },
      {
        "author": "LMB Studio",
        "link_thumb": "https://live.staticflickr.com/65535/51676475235_a1c7c04500_o.gif",
        "link_bin": "https://github.com/lmbstudiocontact/mb4_26/raw/main/Doraemon Anime_L2_653215825_Spanish.bin",
        "name_language": "Spanish",
        "id_bin_language": "Doraemon Anime_L2_653215825_Spanish"
      }
    ],
    "array_tags": [
      "lmbstudio"
    ],
    "list_album": [
      {
        "id_album": "405661392",
        "link_thumb": "https://live.staticflickr.com/65535/51676272964_9e1a78538a_o.gif",
        "title": "Doraemon Anime_L2"
      }
    ]
  },
  {
    "author": "LMB Studio",
    "link_thumb": "https://live.staticflickr.com/65535/51678764209_f0961232ef_o.gif",
    "link_bin": "https://github.com/lmbstudiocontact/mb4_41/raw/main/Football_L9_-469436270.bin",
    "id_bin": "Football_L9_-469436270",
    "list_language": [
      {
        "author": "LMB Studio",
        "link_thumb": "https://live.staticflickr.com/65535/51678344363_2f7c45ec0f_o.gif",
        "link_bin": "https://github.com/lmbstudiocontact/mb4_41/raw/main/Football_L9_-469436270_English.bin",
        "name_language": "English",
        "id_bin_language": "Football_L9_-469436270_English"
      },
      {
        "author": "LMB Studio",
        "link_thumb": "https://live.staticflickr.com/65535/51678764609_dd4acc2c5e_o.gif",
        "link_bin": "https://github.com/lmbstudiocontact/mb4_41/raw/main/Football_L9_-469436270_Portuguese.bin",
        "name_language": "Portuguese",
        "id_bin_language": "Football_L9_-469436270_Portuguese"
      },
      {
        "author": "LMB Studio",
        "link_thumb": "https://live.staticflickr.com/65535/51678764719_8954e3812b_o.gif",
        "link_bin": "https://github.com/lmbstudiocontact/mb4_41/raw/main/Football_L9_-469436270_Russian.bin",
        "name_language": "Russian",
        "id_bin_language": "Football_L9_-469436270_Russian"
      },
      {
        "author": "LMB Studio",
        "link_thumb": "https://live.staticflickr.com/65535/51677291117_1384a7eaac_o.gif",
        "link_bin": "https://github.com/lmbstudiocontact/mb4_41/raw/main/Football_L9_-469436270_Spanish.bin",
        "name_language": "Spanish",
        "id_bin_language": "Football_L9_-469436270_Spanish"
      }
    ],
    "array_tags": [
      "lmbstudio"
    ],
    "list_album": [
      {
        "id_album": "-371026081",
        "link_thumb": "https://live.staticflickr.com/65535/51678764209_f0961232ef_o.gif",
        "title": "Football_L9"
      }
    ]
  }
]